{"af":{"english_name":"Afrikaans"},"am":{"english_name":"Amharic"},"ar":{"english_name":"Arabic"},"ary":{"english_name":"Moroccan Arabic"},"as":{"english_name":"Assamese"},"azb":{"english_name":"South Azerbaijani"},"az":{"english_name":"Azerbaijani"},"bel":{"english_name":"Belarusian"},"bg_bg":{"english_name":"Bulgarian"},"bn_bd":{"english_name":"Bengali (Bangladesh)"},"bo":{"english_name":"Tibetan"},"bs_ba":{"english_name":"Bosnian"},"ca":{"english_name":"Catalan"},"ceb":{"english_name":"Cebuano"},"cs_cz":{"english_name":"Czech"},"cy":{"english_name":"Welsh"},"da_dk":{"english_name":"Danish"},"de_de_formal":{"english_name":"German (Formal)"},"de_de":{"english_name":"German"},"de_at":{"english_name":"German (Austria)"},"de_ch_informal":{"english_name":"German (Switzerland, Informal)"},"de_ch":{"english_name":"German (Switzerland)"},"dsb":{"english_name":"Lower Sorbian"},"dzo":{"english_name":"Dzongkha"},"el":{"english_name":"Greek"},"en_ca":{"english_name":"English (Canada)"},"en_gb":{"english_name":"English (UK)"},"en_za":{"english_name":"English (South Africa)"},"en_au":{"english_name":"English (Australia)"},"en_nz":{"english_name":"English (New Zealand)"},"eo":{"english_name":"Esperanto"},"es_mx":{"english_name":"Spanish (Mexico)"},"es_ve":{"english_name":"Spanish (Venezuela)"},"es_ar":{"english_name":"Spanish (Argentina)"},"es_es":{"english_name":"Spanish (Spain)"},"es_do":{"english_name":"Spanish (Dominican Republic)"},"es_cr":{"english_name":"Spanish (Costa Rica)"},"es_pe":{"english_name":"Spanish (Peru)"},"es_cl":{"english_name":"Spanish (Chile)"},"es_uy":{"english_name":"Spanish (Uruguay)"},"es_pr":{"english_name":"Spanish (Puerto Rico)"},"es_ec":{"english_name":"Spanish (Ecuador)"},"es_gt":{"english_name":"Spanish (Guatemala)"},"es_co":{"english_name":"Spanish (Colombia)"},"et":{"english_name":"Estonian"},"eu":{"english_name":"Basque"},"fa_ir":{"english_name":"Persian"},"fa_af":{"english_name":"Persian (Afghanistan)"},"fi":{"english_name":"Finnish"},"fr_fr":{"english_name":"French (France)"},"fr_ca":{"english_name":"French (Canada)"},"fr_be":{"english_name":"French (Belgium)"},"fur":{"english_name":"Friulian"},"gd":{"english_name":"Scottish Gaelic"},"gl_es":{"english_name":"Galician"},"gu":{"english_name":"Gujarati"},"haz":{"english_name":"Hazaragi"},"he_il":{"english_name":"Hebrew"},"hi_in":{"english_name":"Hindi"},"hr":{"english_name":"Croatian"},"hsb":{"english_name":"Upper Sorbian"},"hu_hu":{"english_name":"Hungarian"},"hy":{"english_name":"Armenian"},"id_id":{"english_name":"Indonesian"},"is_is":{"english_name":"Icelandic"},"it_it":{"english_name":"Italian"},"ja":{"english_name":"Japanese"},"jv_id":{"english_name":"Javanese"},"ka_ge":{"english_name":"Georgian"},"kab":{"english_name":"Kabyle"},"kk":{"english_name":"Kazakh"},"km":{"english_name":"Khmer"},"kn":{"english_name":"Kannada"},"ko_kr":{"english_name":"Korean"},"ckb":{"english_name":"Kurdish (Sorani)"},"lo":{"english_name":"Lao"},"lt_lt":{"english_name":"Lithuanian"},"lv":{"english_name":"Latvian"},"mk_mk":{"english_name":"Macedonian"},"ml_in":{"english_name":"Malayalam"},"mn":{"english_name":"Mongolian"},"mr":{"english_name":"Marathi"},"ms_my":{"english_name":"Malay"},"my_mm":{"english_name":"Myanmar (Burmese)"},"nb_no":{"english_name":"Norwegian (Bokm\u00e5l)"},"ne_np":{"english_name":"Nepali"},"nl_nl":{"english_name":"Dutch"},"nl_nl_formal":{"english_name":"Dutch (Formal)"},"nl_be":{"english_name":"Dutch (Belgium)"},"nn_no":{"english_name":"Norwegian (Nynorsk)"},"oci":{"english_name":"Occitan"},"pa_in":{"english_name":"Punjabi"},"pl_pl":{"english_name":"Polish"},"ps":{"english_name":"Pashto"},"pt_pt":{"english_name":"Portuguese (Portugal)"},"pt_pt_ao90":{"english_name":"Portuguese (Portugal, AO90)"},"pt_ao":{"english_name":"Portuguese (Angola)"},"pt_br":{"english_name":"Portuguese (Brazil)"},"rhg":{"english_name":"Rohingya"},"ro_ro":{"english_name":"Romanian"},"ru_ru":{"english_name":"Russian"},"sah":{"english_name":"Sakha"},"snd":{"english_name":"Sindhi"},"si_lk":{"english_name":"Sinhala"},"sk_sk":{"english_name":"Slovak"},"skr":{"english_name":"Saraiki"},"sl_si":{"english_name":"Slovenian"},"sq":{"english_name":"Albanian"},"sr_rs":{"english_name":"Serbian"},"sv_se":{"english_name":"Swedish"},"sw":{"english_name":"Swahili"},"szl":{"english_name":"Silesian"},"ta_in":{"english_name":"Tamil"},"ta_lk":{"english_name":"Tamil (Sri Lanka)"},"te":{"english_name":"Telugu"},"th":{"english_name":"Thai"},"tl":{"english_name":"Tagalog"},"tr_tr":{"english_name":"Turkish"},"tt_ru":{"english_name":"Tatar"},"tah":{"english_name":"Tahitian"},"ug_cn":{"english_name":"Uighur"},"uk":{"english_name":"Ukrainian"},"ur":{"english_name":"Urdu"},"uz_uz":{"english_name":"Uzbek"},"vi":{"english_name":"Vietnamese"},"zh_tw":{"english_name":"Chinese (Taiwan)"},"zh_cn":{"english_name":"Chinese (China)"},"zh_hk":{"english_name":"Chinese (Hong Kong)"}}